quick_colorlog/__init__.py
quick_colorlog/py.typed
quick_colorlog/quick.py
quick_colorlog-0.0.10.dist-info/METADATA
quick_colorlog-0.0.10.dist-info/WHEEL
quick_colorlog-0.0.10.dist-info/top_level.txt
quick_colorlog-0.0.10.dist-info/RECORD
